[
    {
      "id" : "978-0641723445",
      "name" : "BMO",
      "serialNumber" : "56471-44582",
      "activationCode" : "8994-0968-2140-1352",
      "url" : "sedemoidg2.yourcorp.com:8445/igst",
      "action": "add",
      "online" : true
    },
    {
      "id" : "978-0649723445",
      "name" : "Scotia",
      "serialNumber" : "83785-46710",
      "activationCode" : "2929-9637-1459-1594",
      "url" : "newfie12.qa2016ca.dev.datacard.com:8445/igst",
      "action": "add",
      "online" : true
    }
  ]
